README.rst
setup.cfg
setup.py
pyflapjackevents/__init__.py
pyflapjackevents/client.py
pyflapjackevents/event.py
pyflapjackevents.egg-info/PKG-INFO
pyflapjackevents.egg-info/SOURCES.txt
pyflapjackevents.egg-info/dependency_links.txt
pyflapjackevents.egg-info/entry_points.txt
pyflapjackevents.egg-info/top_level.txt
pyflapjackevents.egg-info/zip-safe