Metadata-Version: 1.0
Name: pyflapjackevents
Version: 0.1
Summary: Send status events to flapjack from python.
Home-page: http://github.com/tuenti/pyflapjackevents
Author: Jose Plana
Author-email: jplana@tuenti.com
License: Apache License, Version 2.0
Platform: UNKNOWN
